LICENSE.txt
README.md
setup.py
playertracker/__init__.py
playertracker.egg-info/PKG-INFO
playertracker.egg-info/SOURCES.txt
playertracker.egg-info/dependency_links.txt
playertracker.egg-info/requires.txt
playertracker.egg-info/top_level.txt