Metadata-Version: 2.1
Name: playertracker
Version: 0.0.4
Summary: A playertracker that checks a code
Home-page: 
Author: Sate
Author-email: sateywatey@proton.me
License: MIT
Keywords: playertracker
Classifier: Development Status :: 5 - Production/Stable
Classifier: Intended Audience :: Developers
Classifier: Operating System :: Microsoft :: Windows :: Windows 10
Classifier: License :: OSI Approved :: MIT License
Classifier: Programming Language :: Python :: 3
License-File: LICENSE.txt
Requires-Dist: requests
Requires-Dist: datetime
